tests/__init__.py
tkmark/__init__.py
tkmark/__main__.py
tkmark/pyrustic_data/backstage/config/build.json
tkmark/pyrustic_data/backstage/config/init.json
tkmark/pyrustic_data/backstage/config/release.json
tkmark/pyrustic_data/backstage/data/github_release_form.json
tkmark/pyrustic_data/backstage/report/build_report.json
tkmark/pyrustic_data/backstage/report/release_report.json
tkmark/pyrustic_data/hubstore/img.json
tkmark/pyrustic_data/hubstore/promotion.json
tkmark-0.0.1.dist-info/LICENSE
tkmark-0.0.1.dist-info/METADATA
tkmark-0.0.1.dist-info/WHEEL
tkmark-0.0.1.dist-info/entry_points.txt
tkmark-0.0.1.dist-info/top_level.txt
tkmark-0.0.1.dist-info/RECORD
