Metadata-Version: 2.1
Name: tkmark
Version: 0.0.1
Summary: Secret
Home-page: https://github.com/pyrustic/pyrustic
Author: Pyrustic Evangelist
Author-email: sapiens@earth.invalid
Maintainer: Pyrustic Evangelist
Maintainer-email: sapiens@earth.invalid
License: MIT
Keywords: desktop-application
Platform: UNKNOWN
Classifier: Programming Language :: Python :: 3
Classifier: License :: OSI Approved :: MIT License
Classifier: Operating System :: OS Independent
Requires-Python: >=3.5
Requires-Dist: pyrustic
